README.rst
setup.py
pyblizzard/__init__.py
pyblizzard/pyblizzard.py
pyblizzard.egg-info/PKG-INFO
pyblizzard.egg-info/SOURCES.txt
pyblizzard.egg-info/dependency_links.txt
pyblizzard.egg-info/requires.txt
pyblizzard.egg-info/top_level.txt
pyblizzard/common/__init__.py
pyblizzard/common/base_community_api.py
pyblizzard/common/enum/__init__.py
pyblizzard/common/enum/locale.py
pyblizzard/common/enum/region.py
pyblizzard/common/utility/__init__.py
pyblizzard/common/utility/urlbuilder.py
pyblizzard/common/utility/util.py
pyblizzard/diablo/__init__.py
pyblizzard/diablo/diablo.py
pyblizzard/diablo/enum/__init__.py
pyblizzard/diablo/enum/artisan.py
pyblizzard/diablo/enum/follower.py
pyblizzard/starcraft2/__init__.py
pyblizzard/starcraft2/starcraft2.py
pyblizzard/wow/__init__.py
pyblizzard/wow/wow.py
pyblizzard/wow/enum/__init__.py
pyblizzard/wow/enum/characterprofilefield.py
pyblizzard/wow/enum/guildprofilefield.py
pyblizzard/wow/enum/pvpbracket.py