Metadata-Version: 1.1
Name: pyblizzard
Version: 1.1
Summary: Python3 wrapper for the Battle.net Community APIs.
Home-page: https://github.com/scb5304/pyblizzard
Author: Steven Brown
Author-email: scb5304@gmail.com
License: UNKNOWN
Download-URL: https://github.com/scb5304/pyblizzard/archive/v1.1.tar.gz
Keywords: python,python3,blizzard,api,wrapper,battle,battle.net
Platform: UNKNOWN
